setup.py
PySychonaut.egg-info/PKG-INFO
PySychonaut.egg-info/SOURCES.txt
PySychonaut.egg-info/dependency_links.txt
PySychonaut.egg-info/requires.txt
PySychonaut.egg-info/top_level.txt
pysychonaut/___init__.py
pysychonaut/py2.py