Metadata-Version: 1.0
Name: PySychonaut
Version: 0.5
Summary: unnoficial erowid, psychonaut wiki and ask_the_caterpillar apis
Home-page: https://github.com/JarbasAl/PySychonaut
Author: jarbasAI
Author-email: jarbasai@mailfence.com
License: MIT
Platform: UNKNOWN
